[{"_id":"5bb52cb2ae55d501a4179e60","device":"xDrip-DexcomG5","date":1538600113021,"dateString":"2018-10-03T23:55:13.021+0300","sgv":73,"direction":"Flat","type":"sgv","filtered":91504,"unfiltered":89632,"rssi":100,"noise":1,"delta":-0.796,"sysTime":"2018-10-03T23:55:13.021+0300"},{"_id":"5bb52b85ae55d501a41788bb","device":"xDrip-DexcomG5","date":1538599811288,"dateString":"2018-10-03T23:50:11.288+0300","sgv":74,"direction":"Flat","type":"sgv","filtered":93536,"unfiltered":90464,"rssi":100,"noise":1,"delta":-1.64,"sysTime":"2018-10-03T23:50:11.288+0300"},{"_id":"5bb52a5bae55d501a4177752","device":"xDrip-DexcomG5","date":1538599512662,"dateString":"2018-10-03T23:45:12.662+0300","sgv":75,"direction":"Flat","type":"sgv","filtered":95888,"unfiltered":92160,"rssi":100,"noise":1,"delta":-2.4,"sysTime":"2018-10-03T23:45:12.662+0300"},{"_id":"5bb5292fae55d501a4176199","device":"xDrip-DexcomG5","date":1538599212476,"dateString":"2018-10-03T23:40:12.476+0300","sgv":78,"direction":"Flat","type":"sgv","filtered":98592,"unfiltered":94656,"rssi":100,"noise":1,"delta":-2.602,"sysTime":"2018-10-03T23:40:12.476+0300"},{"_id":"5bb52803ae55d501a4174ac5","device":"xDrip-DexcomG5","date":1538598912514,"dateString":"2018-10-03T23:35:12.514+0300","sgv":80,"direction":"Flat","type":"sgv","filtered":102032,"unfiltered":97360,"rssi":100,"noise":1,"delta":-3.652,"sysTime":"2018-10-03T23:35:12.514+0300"},{"_id":"5bb525aaae55d501a417213a","device":"xDrip-DexcomG5","date":1538598311772,"dateString":"2018-10-03T23:25:11.772+0300","sgv":88,"direction":"FortyFiveDown","type":"sgv","filtered":114080,"unfiltered":104960,"rssi":100,"noise":1,"delta":-5.022,"sysTime":"2018-10-03T23:25:11.772+0300"},{"_id":"5bb5247eae55d501a4170a09","device":"xDrip-DexcomG5","date":1538598011942,"dateString":"2018-10-03T23:20:11.942+0300","sgv":93,"direction":"FortyFiveDown","type":"sgv","filtered":122688,"unfiltered":110176,"rssi":100,"noise":1,"delta":-5.946,"sysTime":"2018-10-03T23:20:11.942+0300"},{"_id":"5bb52352ae55d501a416f520","device":"xDrip-DexcomG5","date":1538597712076,"dateString":"2018-10-03T23:15:12.076+0300","sgv":98,"direction":"FortyFiveDown","type":"sgv","filtered":131168,"unfiltered":116352,"rssi":100,"noise":1,"delta":-8.255,"sysTime":"2018-10-03T23:15:12.076+0300"},{"_id":"5bb52224ae55d501a416de1c","device":"xDrip-DexcomG5","date":1538597411054,"dateString":"2018-10-03T23:10:11.054+0300","sgv":107,"direction":"FortyFiveDown","type":"sgv","filtered":138592,"unfiltered":124960,"rssi":100,"noise":1,"delta":-7.332,"sysTime":"2018-10-03T23:10:11.054+0300"},{"_id":"5bb51d79ae55d501a4168d1b","device":"xDrip-DexcomG5","date":1538596211659,"dateString":"2018-10-03T22:50:11.659+0300","sgv":136,"direction":"FortyFiveDown","type":"sgv","filtered":165152,"unfiltered":155424,"rssi":100,"noise":1,"delta":-5.317,"sysTime":"2018-10-03T22:50:11.659+0300"},{"_id":"5bb50ab6ae55d501a415492b","device":"xDrip-DexcomG5","date":1538591411540,"dateString":"2018-10-03T21:30:11.540+0300","sgv":221,"direction":"DoubleUp","type":"sgv","filtered":219392,"unfiltered":243840,"rssi":100,"noise":1,"delta":21.691,"sysTime":"2018-10-03T21:30:11.540+0300"},{"_id":"5bb5098aae55d501a4153792","device":"xDrip-DexcomG5","date":1538591111715,"dateString":"2018-10-03T21:25:11.715+0300","sgv":199,"direction":"FortyFiveUp","type":"sgv","filtered":207168,"unfiltered":221312,"rssi":100,"noise":1,"delta":8.992,"sysTime":"2018-10-03T21:25:11.715+0300"},{"_id":"5bb5085fae55d501a4152a10","device":"xDrip-DexcomG5","date":1538590811725,"dateString":"2018-10-03T21:20:11.725+0300","sgv":190,"direction":"FortyFiveUp","type":"sgv","filtered":194048,"unfiltered":211968,"rssi":100,"noise":1,"delta":7.868,"sysTime":"2018-10-03T21:20:11.725+0300"},{"_id":"5bb50734ae55d501a4151768","device":"xDrip-DexcomG5","date":1538590512315,"dateString":"2018-10-03T21:15:12.315+0300","sgv":183,"direction":"SingleUp","type":"sgv","filtered":180288,"unfiltered":203808,"rssi":100,"noise":1,"delta":13.779,"sysTime":"2018-10-03T21:15:12.315+0300"},{"_id":"5bb50606ae55d501a41506fb","device":"xDrip-DexcomG5","date":1538590211969,"dateString":"2018-10-03T21:10:11.969+0300","sgv":169,"direction":"SingleUp","type":"sgv","filtered":168000,"unfiltered":189472,"rssi":100,"noise":1,"delta":15.394,"sysTime":"2018-10-03T21:10:11.969+0300"},{"_id":"5bb504dbae55d501a414f663","device":"xDrip-DexcomG5","date":1538589911919,"dateString":"2018-10-03T21:05:11.919+0300","sgv":153,"direction":"SingleUp","type":"sgv","filtered":158080,"unfiltered":173472,"rssi":100,"noise":1,"delta":10.541,"sysTime":"2018-10-03T21:05:11.919+0300"},{"_id":"5bb503b0ae55d501a414e14c","device":"xDrip-DexcomG5","date":1538589612187,"dateString":"2018-10-03T21:00:12.187+0300","sgv":143,"direction":"FortyFiveUp","type":"sgv","filtered":149344,"unfiltered":162528,"rssi":100,"noise":1,"delta":8.777,"sysTime":"2018-10-03T21:00:12.187+0300"},{"_id":"5bb50284ae55d501a414cc70","device":"xDrip-DexcomG5","date":1538589312234,"dateString":"2018-10-03T20:55:12.234+0300","sgv":134,"direction":"FortyFiveUp","type":"sgv","filtered":139840,"unfiltered":153408,"rssi":100,"noise":1,"delta":9.329,"sysTime":"2018-10-03T20:55:12.234+0300"},{"_id":"5bb50155ae55d501a414b96e","device":"xDrip-DexcomG5","date":1538589011203,"dateString":"2018-10-03T20:50:11.203+0300","sgv":125,"direction":"SingleUp","type":"sgv","filtered":128096,"unfiltered":143680,"rssi":100,"noise":1,"delta":10.055,"sysTime":"2018-10-03T20:50:11.203+0300"},{"_id":"5bb4feffae55d501a4148a86","device":"xDrip-DexcomG5","date":1538588412184,"dateString":"2018-10-03T20:40:12.184+0300","sgv":105,"direction":"SingleUp","type":"sgv","filtered":99568,"unfiltered":122816,"rssi":100,"noise":1,"delta":12.617,"sysTime":"2018-10-03T20:40:12.184+0300"},{"_id":"5bb4fddaae55d501a4147570","device":"xDrip-DexcomG5","date":1538588113087,"dateString":"2018-10-03T20:35:13.087+0300","sgv":92,"direction":"SingleUp","type":"sgv","filtered":88240,"unfiltered":109744,"rssi":100,"noise":1,"delta":13.811,"sysTime":"2018-10-03T20:35:13.087+0300"},{"_id":"5bb4fca7ae55d501a4146056","device":"xDrip-DexcomG5","date":1538587811410,"dateString":"2018-10-03T20:30:11.410+0300","sgv":78,"direction":"SingleUp","type":"sgv","filtered":82032,"unfiltered":95312,"rssi":100,"noise":1,"delta":11.992,"sysTime":"2018-10-03T20:30:11.410+0300"},{"_id":"5bb4fbabae55d501a4144ef9","device":"xDrip-DexcomG5","date":1538587511352,"dateString":"2018-10-03T20:25:11.352+0300","sgv":66,"direction":"Flat","type":"sgv","filtered":80624,"unfiltered":82848,"rssi":100,"noise":1,"delta":2.914,"sysTime":"2018-10-03T20:25:11.352+0300"},{"_id":"5bb4fa4eae55d501a4143ae5","device":"xDrip-DexcomG5","date":1538587211802,"dateString":"2018-10-03T20:20:11.802+0300","sgv":63,"direction":"Flat","type":"sgv","filtered":82224,"unfiltered":79824,"rssi":100,"noise":1,"delta":-1.064,"sysTime":"2018-10-03T20:20:11.802+0300"},{"_id":"5bb4f923ae55d501a414282f","device":"xDrip-DexcomG5","date":1538586912400,"dateString":"2018-10-03T20:15:12.400+0300","sgv":64,"direction":"Flat","type":"sgv","filtered":85248,"unfiltered":80928,"rssi":100,"noise":1,"delta":-2.295,"sysTime":"2018-10-03T20:15:12.400+0300"},{"_id":"5bb4f7f9ae55d501a4141322","device":"xDrip-DexcomG5","date":1538586612487,"dateString":"2018-10-03T20:10:12.487+0300","sgv":67,"direction":"Flat","type":"sgv","filtered":89248,"unfiltered":83312,"rssi":100,"noise":1,"delta":-3.783,"sysTime":"2018-10-03T20:10:12.487+0300"},{"_id":"5bb4f6caae55d501a41400be","device":"xDrip-DexcomG5","date":1538586312109,"dateString":"2018-10-03T20:05:12.109+0300","sgv":70,"direction":"Flat","type":"sgv","filtered":94256,"unfiltered":87248,"rssi":100,"noise":1,"delta":-4.147,"sysTime":"2018-10-03T20:05:12.109+0300"},{"_id":"5bb4f5a0ae55d501a413f110","device":"xDrip-DexcomG5","date":1538586012469,"dateString":"2018-10-03T20:00:12.469+0300","sgv":75,"direction":"FortyFiveDown","type":"sgv","filtered":100432,"unfiltered":91552,"rssi":100,"noise":1,"delta":-5.237,"sysTime":"2018-10-03T20:00:12.469+0300"},{"_id":"5bb4f477ae55d501a413da9b","device":"xDrip-DexcomG5","date":1538585711691,"dateString":"2018-10-03T19:55:11.691+0300","sgv":80,"direction":"FortyFiveDown","type":"sgv","filtered":107968,"unfiltered":97008,"rssi":100,"noise":1,"delta":-6.411,"sysTime":"2018-10-03T19:55:11.691+0300"},{"_id":"5bb4f347ae55d501a413c65f","device":"xDrip-DexcomG5","date":1538585411275,"dateString":"2018-10-03T19:50:11.275+0300","sgv":86,"direction":"FortyFiveDown","type":"sgv","filtered":117312,"unfiltered":103680,"rssi":100,"noise":1,"delta":-8.971,"sysTime":"2018-10-03T19:50:11.275+0300"},{"_id":"5bb4f21aae55d501a413b250","device":"xDrip-DexcomG5","date":1538585111602,"dateString":"2018-10-03T19:45:11.602+0300","sgv":95,"direction":"FortyFiveDown","type":"sgv","filtered":128912,"unfiltered":112992,"rssi":100,"noise":1,"delta":-9.432,"sysTime":"2018-10-03T19:45:11.602+0300"},{"_id":"5bb4f0efae55d501a4139b9a","device":"xDrip-DexcomG5","date":1538584812872,"dateString":"2018-10-03T19:40:12.872+0300","sgv":105,"direction":"SingleDown","type":"sgv","filtered":142432,"unfiltered":122752,"rssi":100,"noise":1,"delta":-10.729,"sysTime":"2018-10-03T19:40:12.872+0300"},{"_id":"5bb4efc2ae55d501a413877f","device":"xDrip-DexcomG5","date":1538584511514,"dateString":"2018-10-03T19:35:11.514+0300","sgv":115,"direction":"SingleDown","type":"sgv","filtered":156320,"unfiltered":133952,"rssi":100,"noise":1,"delta":-13.043,"sysTime":"2018-10-03T19:35:11.514+0300"},{"_id":"5bb4ee97ae55d501a413718d","device":"xDrip-DexcomG5","date":1538584211216,"dateString":"2018-10-03T19:30:11.216+0300","sgv":128,"direction":"SingleDown","type":"sgv","filtered":168096,"unfiltered":147520,"rssi":100,"noise":1,"delta":-13.284,"sysTime":"2018-10-03T19:30:11.216+0300"},{"_id":"5bb4ed6fae55d501a4135ad6","device":"xDrip-DexcomG5","date":1538583911499,"dateString":"2018-10-03T19:25:11.499+0300","sgv":142,"direction":"SingleDown","type":"sgv","filtered":175872,"unfiltered":161312,"rssi":100,"noise":1,"delta":-10.329,"sysTime":"2018-10-03T19:25:11.499+0300"},{"_id":"5bb4ec3fae55d501a41345b8","device":"xDrip-DexcomG5","date":1538583611882,"dateString":"2018-10-03T19:20:11.882+0300","sgv":152,"direction":"FortyFiveDown","type":"sgv","filtered":180064,"unfiltered":172032,"rssi":100,"noise":1,"delta":-8.168,"sysTime":"2018-10-03T19:20:11.882+0300"},{"_id":"5bb4eb16ae55d501a41332ce","device":"xDrip-DexcomG5","date":1538583313303,"dateString":"2018-10-03T19:15:13.303+0300","sgv":160,"direction":"Flat","type":"sgv","filtered":182880,"unfiltered":180480,"rssi":100,"noise":1,"delta":-2.278,"sysTime":"2018-10-03T19:15:13.303+0300"},{"_id":"5bb4e78fae55d501a412f0a4","device":"xDrip-DexcomG5","date":1538582412974,"dateString":"2018-10-03T19:00:12.974+0300","sgv":167,"direction":"FortyFiveDown","type":"sgv","filtered":200128,"unfiltered":187584,"rssi":100,"noise":1,"delta":-9.213,"sysTime":"2018-10-03T19:00:12.974+0300"},{"_id":"5bb4e539ae55d501a412c636","device":"xDrip-DexcomG5","date":1538581814329,"dateString":"2018-10-03T18:50:14.329+0300","sgv":185,"direction":"FortyFiveDown","type":"sgv","filtered":221120,"unfiltered":206688,"rssi":100,"noise":1,"delta":-6.655,"sysTime":"2018-10-03T18:50:14.329+0300"},{"_id":"5bb4e409ae55d501a412b0dd","device":"xDrip-DexcomG5","date":1538581511715,"dateString":"2018-10-03T18:45:11.715+0300","sgv":192,"direction":"SingleDown","type":"sgv","filtered":234464,"unfiltered":213664,"rssi":100,"noise":1,"delta":-12.41,"sysTime":"2018-10-03T18:45:11.715+0300"},{"_id":"5bb4e1b3ae55d501a412849d","device":"xDrip-DexcomG5","date":1538580912460,"dateString":"2018-10-03T18:35:12.460+0300","sgv":217,"direction":"SingleDown","type":"sgv","filtered":256704,"unfiltered":239424,"rssi":100,"noise":1,"delta":-11.938,"sysTime":"2018-10-03T18:35:12.460+0300"},{"_id":"5bb4e088ae55d501a4126fa1","device":"xDrip-DexcomG5","date":1538580612978,"dateString":"2018-10-03T18:30:12.978+0300","sgv":229,"direction":"FortyFiveDown","type":"sgv","filtered":262976,"unfiltered":251808,"rssi":100,"noise":1,"delta":-9.864,"sysTime":"2018-10-03T18:30:12.978+0300"},{"_id":"5bb4df65ae55d501a41259fe","device":"xDrip-DexcomG5","date":1538580312339,"dateString":"2018-10-03T18:25:12.339+0300","sgv":239,"direction":"FortyFiveDown","type":"sgv","filtered":268352,"unfiltered":262079.99999999997,"rssi":100,"noise":1,"delta":-5.832,"sysTime":"2018-10-03T18:25:12.339+0300"},{"_id":"5bb4de31ae55d501a41245a4","device":"xDrip-DexcomG5","date":1538580014558,"dateString":"2018-10-03T18:20:14.558+0300","sgv":244,"direction":"FortyFiveDown","type":"sgv","filtered":275200,"unfiltered":268096,"rssi":100,"noise":1,"delta":-6.643,"sysTime":"2018-10-03T18:20:14.558+0300"},{"_id":"5bb4d855ae55d501a411f392","device":"xDrip-DexcomG5","date":1538578512595,"dateString":"2018-10-03T17:55:12.595+0300","sgv":278,"direction":"Flat","type":"sgv","filtered":306560,"unfiltered":302656,"rssi":100,"noise":1,"delta":-1.165,"sysTime":"2018-10-03T17:55:12.595+0300"},{"_id":"5bb4d727ae55d501a411e828","device":"xDrip-DexcomG5","date":1538578211243,"dateString":"2018-10-03T17:50:11.243+0300","sgv":279,"direction":"FortyFiveDown","type":"sgv","filtered":311744,"unfiltered":303872,"rssi":100,"noise":1,"delta":-5.441,"sysTime":"2018-10-03T17:50:11.243+0300"},{"_id":"5bb4d5fcae55d501a411db43","device":"xDrip-DexcomG5","date":1538577912446,"dateString":"2018-10-03T17:45:12.446+0300","sgv":284,"direction":"Flat","type":"sgv","filtered":317632,"unfiltered":309504,"rssi":100,"noise":1,"delta":-2.34,"sysTime":"2018-10-03T17:45:12.446+0300"},{"_id":"5bb4d4cfae55d501a411ca01","device":"xDrip-DexcomG5","date":1538577612390,"dateString":"2018-10-03T17:40:12.390+0300","sgv":287,"direction":"SingleDown","type":"sgv","filtered":323648,"unfiltered":311936,"rssi":100,"noise":1,"delta":-10.969,"sysTime":"2018-10-03T17:40:12.390+0300"},{"_id":"5bb4d3a3ae55d501a411bdb7","device":"xDrip-DexcomG5","date":1538577312573,"dateString":"2018-10-03T17:35:12.573+0300","sgv":298,"direction":"Flat","type":"sgv","filtered":329024,"unfiltered":323328,"rssi":100,"noise":1,"delta":-0.86,"sysTime":"2018-10-03T17:35:12.573+0300"},{"_id":"5bb4d276ae55d501a411ad1d","device":"xDrip-DexcomG5","date":1538577011885,"dateString":"2018-10-03T17:30:11.885+0300","sgv":299,"direction":"FortyFiveDown","type":"sgv","filtered":332928,"unfiltered":324224,"rssi":100,"noise":1,"delta":-6.334,"sysTime":"2018-10-03T17:30:11.885+0300"},{"_id":"5bb4d14bae55d501a4119ebc","device":"xDrip-DexcomG5","date":1538576711427,"dateString":"2018-10-03T17:25:11.427+0300","sgv":305,"direction":"Flat","type":"sgv","filtered":334400,"unfiltered":330816,"rssi":100,"noise":1,"delta":-2.899,"sysTime":"2018-10-03T17:25:11.427+0300"},{"_id":"5bb4d020ae55d501a4118cdd","device":"xDrip-DexcomG5","date":1538576411882,"dateString":"2018-10-03T17:20:11.882+0300","sgv":308,"direction":"Flat","type":"sgv","filtered":332416,"unfiltered":333824,"rssi":100,"noise":1,"delta":0.491,"sysTime":"2018-10-03T17:20:11.882+0300"},{"_id":"5bb4cef3ae55d501a4118104","device":"xDrip-DexcomG5","date":1538576111053,"dateString":"2018-10-03T17:15:11.053+0300","sgv":307,"direction":"Flat","type":"sgv","filtered":327936,"unfiltered":333312,"rssi":100,"noise":1,"delta":-0.062,"sysTime":"2018-10-03T17:15:11.053+0300"},{"_id":"5bb4cdc9ae55d501a4117421","device":"xDrip-DexcomG5","date":1538575811949,"dateString":"2018-10-03T17:10:11.949+0300","sgv":307,"direction":"FortyFiveUp","type":"sgv","filtered":322944,"unfiltered":333376,"rssi":100,"noise":1,"delta":8.427,"sysTime":"2018-10-03T17:10:11.949+0300"},{"_id":"5bb4cb72ae55d501a4115c60","device":"xDrip-DexcomG5","date":1538575213409,"dateString":"2018-10-03T17:00:13.409+0300","sgv":291,"direction":"Flat","type":"sgv","filtered":312192,"unfiltered":315904,"rssi":100,"noise":1,"delta":-0.923,"sysTime":"2018-10-03T17:00:13.409+0300"},{"_id":"5bb4ca46ae55d501a4115194","device":"xDrip-DexcomG5","date":1538574913071,"dateString":"2018-10-03T16:55:13.071+0300","sgv":291,"direction":"FortyFiveUp","type":"sgv","filtered":305024,"unfiltered":316864,"rssi":100,"noise":1,"delta":6.161,"sysTime":"2018-10-03T16:55:13.071+0300"},{"_id":"5bb4c91cae55d501a411448a","device":"xDrip-DexcomG5","date":1538574613195,"dateString":"2018-10-03T16:50:13.195+0300","sgv":285,"direction":"FortyFiveUp","type":"sgv","filtered":297152,"unfiltered":310464,"rssi":100,"noise":1,"delta":8.541,"sysTime":"2018-10-03T16:50:13.195+0300"},{"_id":"5bb4c7eaae55d501a4113ab0","device":"xDrip-DexcomG5","date":1538574312497,"dateString":"2018-10-03T16:45:12.497+0300","sgv":277,"direction":"FortyFiveUp","type":"sgv","filtered":290432,"unfiltered":301568,"rssi":100,"noise":1,"delta":7.19,"sysTime":"2018-10-03T16:45:12.497+0300"},{"_id":"5bb4c594ae55d501a4112d9f","device":"xDrip-DexcomG5","date":1538573713726,"dateString":"2018-10-03T16:35:13.726+0300","sgv":262,"direction":"Flat","type":"sgv","filtered":280448,"unfiltered":286656,"rssi":100,"noise":1,"delta":4.098,"sysTime":"2018-10-03T16:35:13.726+0300"},{"_id":"5bb4c467ae55d501a4112692","device":"xDrip-DexcomG5","date":1538573411623,"dateString":"2018-10-03T16:30:11.623+0300","sgv":258,"direction":"Flat","type":"sgv","filtered":275264,"unfiltered":282368,"rssi":100,"noise":1,"delta":4.005,"sysTime":"2018-10-03T16:30:11.623+0300"},{"_id":"5bb4c339ae55d501a4111efd","device":"xDrip-DexcomG5","date":1538573111729,"dateString":"2018-10-03T16:25:11.729+0300","sgv":254,"direction":"FortyFiveUp","type":"sgv","filtered":268992,"unfiltered":278208,"rssi":100,"noise":1,"delta":5.768,"sysTime":"2018-10-03T16:25:11.729+0300"},{"_id":"5bb4c0e3ae55d501a4111019","device":"xDrip-DexcomG5","date":1538572512691,"dateString":"2018-10-03T16:15:12.691+0300","sgv":243,"direction":"FortyFiveUp","type":"sgv","filtered":254656,"unfiltered":266240,"rssi":100,"noise":1,"delta":7.032,"sysTime":"2018-10-03T16:15:12.691+0300"},{"_id":"5bb4bfb6ae55d501a4110889","device":"xDrip-DexcomG5","date":1538572211873,"dateString":"2018-10-03T16:10:11.873+0300","sgv":236,"direction":"FortyFiveUp","type":"sgv","filtered":248160,"unfiltered":258911.99999999997,"rssi":100,"noise":1,"delta":6.554,"sysTime":"2018-10-03T16:10:11.873+0300"},{"_id":"5bb4bd5eae55d501a410f9a1","device":"xDrip-DexcomG5","date":1538571611380,"dateString":"2018-10-03T16:00:11.380+0300","sgv":223,"direction":"FortyFiveUp","type":"sgv","filtered":238464,"unfiltered":245280,"rssi":100,"noise":1,"delta":5.023,"sysTime":"2018-10-03T16:00:11.380+0300"},{"_id":"5bb4bc50ae55d501a410f386","device":"xDrip-DexcomG5","date":1538571311627,"dateString":"2018-10-03T15:55:11.627+0300","sgv":218,"direction":"Flat","type":"sgv","filtered":234464,"unfiltered":240064,"rssi":100,"noise":1,"delta":3.33,"sysTime":"2018-10-03T15:55:11.627+0300"},{"_id":"5bb4bb07ae55d501a410ec5f","device":"xDrip-DexcomG5","date":1538571012050,"dateString":"2018-10-03T15:50:12.050+0300","sgv":214,"direction":"Flat","type":"sgv","filtered":230496,"unfiltered":236608,"rssi":100,"noise":1,"delta":3.441,"sysTime":"2018-10-03T15:50:12.050+0300"},{"_id":"5bb4b9d9ae55d501a410e5da","device":"xDrip-DexcomG5","date":1538570711354,"dateString":"2018-10-03T15:45:11.354+0300","sgv":211,"direction":"Flat","type":"sgv","filtered":226656,"unfiltered":233024,"rssi":100,"noise":1,"delta":3.848,"sysTime":"2018-10-03T15:45:11.354+0300"},{"_id":"5bb4b783ae55d501a410d883","device":"xDrip-DexcomG5","date":1538570113635,"dateString":"2018-10-03T15:35:13.635+0300","sgv":203,"direction":"Flat","type":"sgv","filtered":220416,"unfiltered":225056,"rssi":100,"noise":1,"delta":2.513,"sysTime":"2018-10-03T15:35:13.635+0300"},{"_id":"5bb4b52dae55d501a410ca55","device":"xDrip-DexcomG5","date":1538569514550,"dateString":"2018-10-03T15:25:14.550+0300","sgv":198,"direction":"Flat","type":"sgv","filtered":217312,"unfiltered":219840,"rssi":100,"noise":1,"delta":1.924,"sysTime":"2018-10-03T15:25:14.550+0300"},{"_id":"5bb4b3ffae55d501a410c36b","device":"xDrip-DexcomG5","date":1538569212047,"dateString":"2018-10-03T15:20:12.047+0300","sgv":196,"direction":"Flat","type":"sgv","filtered":217472,"unfiltered":217824,"rssi":100,"noise":1,"delta":0.493,"sysTime":"2018-10-03T15:20:12.047+0300"},{"_id":"5bb4b2d3ae55d501a410bd47","device":"xDrip-DexcomG5","date":1538568911994,"dateString":"2018-10-03T15:15:11.994+0300","sgv":196,"direction":"Flat","type":"sgv","filtered":218304,"unfiltered":217312,"rssi":100,"noise":1,"delta":0.369,"sysTime":"2018-10-03T15:15:11.994+0300"},{"_id":"5bb4b1a7ae55d501a410b6fa","device":"xDrip-DexcomG5","date":1538568611881,"dateString":"2018-10-03T15:10:11.881+0300","sgv":195,"direction":"Flat","type":"sgv","filtered":218592,"unfiltered":216928,"rssi":100,"noise":1,"delta":-1.05,"sysTime":"2018-10-03T15:10:11.881+0300"},{"_id":"5bb4b07cae55d501a410b0b9","device":"xDrip-DexcomG5","date":1538568312763,"dateString":"2018-10-03T15:05:12.763+0300","sgv":196,"direction":"Flat","type":"sgv","filtered":217344,"unfiltered":218016,"rssi":100,"noise":1,"delta":-0.246,"sysTime":"2018-10-03T15:05:12.763+0300"},{"_id":"5bb4af4eae55d501a410aa12","device":"xDrip-DexcomG5","date":1538568012014,"dateString":"2018-10-03T15:00:12.014+0300","sgv":197,"direction":"Flat","type":"sgv","filtered":213952,"unfiltered":218272,"rssi":100,"noise":1,"delta":2.043,"sysTime":"2018-10-03T15:00:12.014+0300"},{"_id":"5bb4ae24ae55d501a410a3e1","device":"xDrip-DexcomG5","date":1538567713644,"dateString":"2018-10-03T14:55:13.644+0300","sgv":195,"direction":"Flat","type":"sgv","filtered":208896,"unfiltered":216160,"rssi":100,"noise":1,"delta":3.897,"sysTime":"2018-10-03T14:55:13.644+0300"},{"_id":"5bb4acf7ae55d501a4109db0","device":"xDrip-DexcomG5","date":1538567412552,"dateString":"2018-10-03T14:50:12.552+0300","sgv":191,"direction":"Flat","type":"sgv","filtered":203616,"unfiltered":212096,"rssi":100,"noise":1,"delta":3.348,"sysTime":"2018-10-03T14:50:12.552+0300"},{"_id":"5bb4abcbae55d501a41097ce","device":"xDrip-DexcomG5","date":1538567111774,"dateString":"2018-10-03T14:45:11.774+0300","sgv":187,"direction":"FortyFiveUp","type":"sgv","filtered":199360,"unfiltered":208608,"rssi":100,"noise":1,"delta":7.327,"sysTime":"2018-10-03T14:45:11.774+0300"},{"_id":"5bb4aaa0ae55d501a4109217","device":"xDrip-DexcomG5","date":1538566811707,"dateString":"2018-10-03T14:40:11.707+0300","sgv":180,"direction":"FortyFiveUp","type":"sgv","filtered":195616,"unfiltered":200992,"rssi":100,"noise":1,"delta":5.458,"sysTime":"2018-10-03T14:40:11.707+0300"},{"_id":"5bb4a973ae55d501a4108c60","device":"xDrip-DexcomG5","date":1538566512126,"dateString":"2018-10-03T14:35:12.126+0300","sgv":174,"direction":"Flat","type":"sgv","filtered":190400,"unfiltered":195328,"rssi":100,"noise":1,"delta":3.662,"sysTime":"2018-10-03T14:35:12.126+0300"},{"_id":"5bb4a71cae55d501a4107fc9","device":"xDrip-DexcomG5","date":1538565914297,"dateString":"2018-10-03T14:25:14.297+0300","sgv":167,"direction":"SingleUp","type":"sgv","filtered":170560,"unfiltered":187744,"rssi":100,"noise":1,"delta":11.284,"sysTime":"2018-10-03T14:25:14.297+0300"},{"_id":"5bb4a39aae55d501a4106c3e","device":"xDrip-DexcomG5","date":1538565013749,"dateString":"2018-10-03T14:10:13.749+0300","sgv":133,"direction":"SingleUp","type":"sgv","filtered":136288,"unfiltered":152544,"rssi":100,"noise":1,"delta":10.502,"sysTime":"2018-10-03T14:10:13.749+0300"},{"_id":"5bb4a26dae55d501a41065b2","device":"xDrip-DexcomG5","date":1538564712922,"dateString":"2018-10-03T14:05:12.922+0300","sgv":123,"direction":"SingleUp","type":"sgv","filtered":125360,"unfiltered":141600,"rssi":100,"noise":1,"delta":10.811,"sysTime":"2018-10-03T14:05:12.922+0300"},{"_id":"5bb4a140ae55d501a4105edf","device":"xDrip-DexcomG5","date":1538564412985,"dateString":"2018-10-03T14:00:12.985+0300","sgv":112,"direction":"FortyFiveUp","type":"sgv","filtered":113392,"unfiltered":130368,"rssi":100,"noise":1,"delta":9.737,"sysTime":"2018-10-03T14:00:12.985+0300"},{"_id":"5bb4a013ae55d501a4105816","device":"xDrip-DexcomG5","date":1538564112702,"dateString":"2018-10-03T13:55:12.702+0300","sgv":102,"direction":"SingleUp","type":"sgv","filtered":100576,"unfiltered":120240,"rssi":100,"noise":1,"delta":10.352,"sysTime":"2018-10-03T13:55:12.702+0300"},{"_id":"5bb49dccae55d501a4104a88","device":"xDrip-DexcomG5","date":1538563516591,"dateString":"2018-10-03T13:45:16.591+0300","sgv":82,"direction":"SingleUp","type":"sgv","filtered":81584,"unfiltered":98864,"rssi":100,"noise":1,"delta":10.08,"sysTime":"2018-10-03T13:45:16.591+0300"},{"_id":"5bb49b64ae55d501a4103c5e","device":"xDrip-DexcomG5","date":1538562913557,"dateString":"2018-10-03T13:35:13.557+0300","sgv":61,"direction":"Flat","type":"sgv","filtered":80144,"unfiltered":77808,"rssi":100,"noise":1,"delta":-1.178,"sysTime":"2018-10-03T13:35:13.557+0300"},{"_id":"5bb4992eae55d501a4102dde","device":"xDrip-DexcomG5","date":1538562313783,"dateString":"2018-10-03T13:25:13.783+0300","sgv":64,"direction":"Flat","type":"sgv","filtered":82464,"unfiltered":80256,"rssi":100,"noise":1,"delta":-1.857,"sysTime":"2018-10-03T13:25:13.783+0300"},{"_id":"5bb497e2ae55d501a4102507","device":"xDrip-DexcomG5","date":1538562012857,"dateString":"2018-10-03T13:20:12.857+0300","sgv":66,"direction":"Flat","type":"sgv","filtered":81040,"unfiltered":82192,"rssi":100,"noise":1,"delta":0.077,"sysTime":"2018-10-03T13:20:12.857+0300"},{"_id":"5bb496b5ae55d501a4101cf0","device":"xDrip-DexcomG5","date":1538561712050,"dateString":"2018-10-03T13:15:12.050+0300","sgv":66,"direction":"Flat","type":"sgv","filtered":78608,"unfiltered":82112,"rssi":100,"noise":1,"delta":0.586,"sysTime":"2018-10-03T13:15:12.050+0300"},{"_id":"5bb49587ae55d501a41014d3","device":"xDrip-DexcomG5","date":1538561412438,"dateString":"2018-10-03T13:10:12.438+0300","sgv":65,"direction":"Flat","type":"sgv","filtered":77376,"unfiltered":81504,"rssi":100,"noise":1,"delta":2.22,"sysTime":"2018-10-03T13:10:12.438+0300"},{"_id":"5bb4945bae55d501a4100cac","device":"xDrip-DexcomG5","date":1538561112851,"dateString":"2018-10-03T13:05:12.851+0300","sgv":63,"direction":"Flat","type":"sgv","filtered":79648,"unfiltered":79200,"rssi":100,"noise":1,"delta":0.784,"sysTime":"2018-10-03T13:05:12.851+0300"},{"_id":"5bb4932fae55d501a410047b","device":"xDrip-DexcomG5","date":1538560812460,"dateString":"2018-10-03T13:00:12.460+0300","sgv":62,"direction":"Flat","type":"sgv","filtered":86592,"unfiltered":78384,"rssi":100,"noise":1,"delta":-3.325,"sysTime":"2018-10-03T13:00:12.460+0300"},{"_id":"5bb49205ae55d501a40ffc80","device":"xDrip-DexcomG5","date":1538560515147,"dateString":"2018-10-03T12:55:15.147+0300","sgv":65,"direction":"FortyFiveDown","type":"sgv","filtered":97232,"unfiltered":81808,"rssi":100,"noise":1,"delta":-9.921,"sysTime":"2018-10-03T12:55:15.147+0300"},{"_id":"5bb48fb0ae55d501a40fef48","device":"xDrip-DexcomG5","date":1538559917374,"dateString":"2018-10-03T12:45:17.374+0300","sgv":85,"direction":"SingleDown","type":"sgv","filtered":122128,"unfiltered":102352,"rssi":100,"noise":1,"delta":-13.014,"sysTime":"2018-10-03T12:45:17.374+0300"},{"_id":"5bb48e81ae55d501a40fe89f","device":"xDrip-DexcomG5","date":1538559614614,"dateString":"2018-10-03T12:40:14.614+0300","sgv":98,"direction":"SingleDown","type":"sgv","filtered":134656,"unfiltered":116000,"rssi":100,"noise":1,"delta":-12.209,"sysTime":"2018-10-03T12:40:14.614+0300"},{"_id":"5bb48d52ae55d501a40fe21b","device":"xDrip-DexcomG5","date":1538559312331,"dateString":"2018-10-03T12:35:12.331+0300","sgv":110,"direction":"SingleDown","type":"sgv","filtered":147456,"unfiltered":128783.99999999999,"rssi":100,"noise":1,"delta":-11.052,"sysTime":"2018-10-03T12:35:12.331+0300"},{"_id":"5bb48c28ae55d501a40fdbac","device":"xDrip-DexcomG5","date":1538559013501,"dateString":"2018-10-03T12:30:13.501+0300","sgv":121,"direction":"SingleDown","type":"sgv","filtered":160128,"unfiltered":140224,"rssi":100,"noise":1,"delta":-11.373,"sysTime":"2018-10-03T12:30:13.501+0300"},{"_id":"5bb48afaae55d501a40fd507","device":"xDrip-DexcomG5","date":1538558712957,"dateString":"2018-10-03T12:25:12.957+0300","sgv":133,"direction":"SingleDown","type":"sgv","filtered":171936,"unfiltered":152064,"rssi":100,"noise":1,"delta":-10.578,"sysTime":"2018-10-03T12:25:12.957+0300"},{"_id":"5bb4864bae55d501a40fb9ee","device":"xDrip-DexcomG5","date":1538557512174,"dateString":"2018-10-03T12:05:12.174+0300","sgv":175,"direction":"FortyFiveDown","type":"sgv","filtered":209056,"unfiltered":196064,"rssi":100,"noise":1,"delta":-8.121,"sysTime":"2018-10-03T12:05:12.174+0300"},{"_id":"5bb48521ae55d501a40fb260","device":"xDrip-DexcomG5","date":1538557214153,"dateString":"2018-10-03T12:00:14.153+0300","sgv":183,"direction":"FortyFiveDown","type":"sgv","filtered":213664,"unfiltered":204448,"rssi":100,"noise":1,"delta":-7.544,"sysTime":"2018-10-03T12:00:14.153+0300"},{"_id":"5bb483f2ae55d501a40faab9","device":"xDrip-DexcomG5","date":1538556912911,"dateString":"2018-10-03T11:55:12.911+0300","sgv":191,"direction":"Flat","type":"sgv","filtered":215584,"unfiltered":212320,"rssi":100,"noise":1,"delta":-0.421,"sysTime":"2018-10-03T11:55:12.911+0300"},{"_id":"5bb4806fae55d501a40f9445","device":"xDrip-DexcomG5","date":1538556012220,"dateString":"2018-10-03T11:40:12.220+0300","sgv":192,"direction":"Flat","type":"sgv","filtered":211072,"unfiltered":213632,"rssi":100,"noise":1,"delta":0.279,"sysTime":"2018-10-03T11:40:12.220+0300"},{"_id":"5bb47f45ae55d501a40f8ccb","device":"xDrip-DexcomG5","date":1538555714035,"dateString":"2018-10-03T11:35:14.035+0300","sgv":192,"direction":"Flat","type":"sgv","filtered":206528,"unfiltered":213344,"rssi":100,"noise":1,"delta":4.497,"sysTime":"2018-10-03T11:35:14.035+0300"},{"_id":"5bb47ceaae55d501a40f7f9d","device":"xDrip-DexcomG5","date":1538555112183,"dateString":"2018-10-03T11:25:12.183+0300","sgv":183,"direction":"Flat","type":"sgv","filtered":195744,"unfiltered":203968,"rssi":100,"noise":1,"delta":4.752,"sysTime":"2018-10-03T11:25:12.183+0300"},{"_id":"5bb4783bae55d501a40f605b","device":"xDrip-DexcomG5","date":1538553912760,"dateString":"2018-10-03T11:05:12.760+0300","sgv":164,"direction":"FortyFiveUp","type":"sgv","filtered":178240,"unfiltered":184224,"rssi":100,"noise":1,"delta":6.882,"sysTime":"2018-10-03T11:05:12.760+0300"},{"_id":"5bb4725eae55d501a40f3cf4","device":"xDrip-DexcomG5","date":1538552412020,"dateString":"2018-10-03T10:40:12.020+0300","sgv":129,"direction":"SingleUp","type":"sgv","filtered":129632,"unfiltered":148448,"rssi":100,"noise":1,"delta":10.533,"sysTime":"2018-10-03T10:40:12.020+0300"},{"_id":"5bb46edaae55d501a40f29c8","device":"xDrip-DexcomG5","date":1538551512146,"dateString":"2018-10-03T10:25:12.146+0300","sgv":98,"direction":"FortyFiveUp","type":"sgv","filtered":104032,"unfiltered":115616,"rssi":100,"noise":1,"delta":6.946,"sysTime":"2018-10-03T10:25:12.146+0300"},{"_id":"5bb46c83ae55d501a40f1cd9","device":"xDrip-DexcomG5","date":1538550912326,"dateString":"2018-10-03T10:15:12.326+0300","sgv":84,"direction":"Flat","type":"sgv","filtered":99872,"unfiltered":101184,"rssi":100,"noise":1,"delta":2.446,"sysTime":"2018-10-03T10:15:12.326+0300"},{"_id":"5bb46b5aae55d501a40f1644","device":"xDrip-DexcomG5","date":1538550615874,"dateString":"2018-10-03T10:10:15.874+0300","sgv":81,"direction":"Flat","type":"sgv","filtered":101840,"unfiltered":98672,"rssi":100,"noise":1,"delta":-1.447,"sysTime":"2018-10-03T10:10:15.874+0300"},{"_id":"5bb46a2aae55d501a40f0f81","device":"xDrip-DexcomG5","date":1538550312593,"dateString":"2018-10-03T10:05:12.593+0300","sgv":83,"direction":"Flat","type":"sgv","filtered":104256,"unfiltered":100192,"rssi":100,"noise":1,"delta":-2.458,"sysTime":"2018-10-03T10:05:12.593+0300"},{"_id":"5bb467d3ae55d501a40f0103","device":"xDrip-DexcomG5","date":1538549713122,"dateString":"2018-10-03T09:55:13.122+0300","sgv":88,"direction":"Flat","type":"sgv","filtered":106432,"unfiltered":105296,"rssi":100,"noise":1,"delta":-0.74,"sysTime":"2018-10-03T09:55:13.122+0300"},{"_id":"5bb4657bae55d501a40ef038","device":"xDrip-DexcomG5","date":1538549113989,"dateString":"2018-10-03T09:45:13.989+0300","sgv":89,"direction":"Flat","type":"sgv","filtered":106128,"unfiltered":106832,"rssi":100,"noise":1,"delta":0.354,"sysTime":"2018-10-03T09:45:13.989+0300"},{"_id":"5bb46323ae55d501a40ede30","device":"xDrip-DexcomG5","date":1538548512984,"dateString":"2018-10-03T09:35:12.984+0300","sgv":89,"direction":"Flat","type":"sgv","filtered":107680,"unfiltered":106096,"rssi":100,"noise":1,"delta":-0.833,"sysTime":"2018-10-03T09:35:12.984+0300"},{"_id":"5bb461f8ae55d501a40ed516","device":"xDrip-DexcomG5","date":1538548213575,"dateString":"2018-10-03T09:30:13.575+0300","sgv":89,"direction":"Flat","type":"sgv","filtered":109136,"unfiltered":106960,"rssi":100,"noise":1,"delta":-1.201,"sysTime":"2018-10-03T09:30:13.575+0300"},{"_id":"5bb460daae55d501a40ecc7b","device":"xDrip-DexcomG5","date":1538547913660,"dateString":"2018-10-03T09:25:13.660+0300","sgv":91,"direction":"Flat","type":"sgv","filtered":110672,"unfiltered":108208,"rssi":100,"noise":1,"delta":-1.463,"sysTime":"2018-10-03T09:25:13.660+0300"},{"_id":"5bb45fa1ae55d501a40ec434","device":"xDrip-DexcomG5","date":1538547613824,"dateString":"2018-10-03T09:20:13.824+0300","sgv":92,"direction":"Flat","type":"sgv","filtered":112096,"unfiltered":109728,"rssi":100,"noise":1,"delta":-1.524,"sysTime":"2018-10-03T09:20:13.824+0300"},{"_id":"5bb45c1dae55d501a40eadca","device":"xDrip-DexcomG5","date":1538546713459,"dateString":"2018-10-03T09:05:13.459+0300","sgv":97,"direction":"Flat","type":"sgv","filtered":116480,"unfiltered":114480,"rssi":100,"noise":1,"delta":-1.449,"sysTime":"2018-10-03T09:05:13.459+0300"},{"_id":"5bb4589aae55d501a40e9a45","device":"xDrip-DexcomG5","date":1538545814809,"dateString":"2018-10-03T08:50:14.809+0300","sgv":101,"direction":"Flat","type":"sgv","filtered":120544,"unfiltered":118992,"rssi":100,"noise":1,"delta":-0.653,"sysTime":"2018-10-03T08:50:14.809+0300"},{"_id":"5bb45640ae55d501a40e8d37","device":"xDrip-DexcomG5","date":1538545213405,"dateString":"2018-10-03T08:40:13.405+0300","sgv":102,"direction":"Flat","type":"sgv","filtered":120288,"unfiltered":120352,"rssi":100,"noise":1,"delta":0.918,"sysTime":"2018-10-03T08:40:13.405+0300"},{"_id":"5bb45064ae55d501a40e6aa0","device":"xDrip-DexcomG5","date":1538543713493,"dateString":"2018-10-03T08:15:13.493+0300","sgv":98,"direction":"Flat","type":"sgv","filtered":112800,"unfiltered":115584,"rssi":100,"noise":1,"delta":-0.142,"sysTime":"2018-10-03T08:15:13.493+0300"},{"_id":"5bb445d8ae55d501a40e2829","device":"xDrip-DexcomG5","date":1538541013257,"dateString":"2018-10-03T07:30:13.257+0300","sgv":99,"direction":"Flat","type":"sgv","filtered":122064,"unfiltered":116912,"rssi":100,"noise":1,"delta":-3.497,"sysTime":"2018-10-03T07:30:13.257+0300"},{"_id":"5bb44000ae55d501a40e0786","device":"xDrip-DexcomG5","date":1538539513979,"dateString":"2018-10-03T07:05:13.979+0300","sgv":116,"direction":"Flat","type":"sgv","filtered":137984,"unfiltered":135072,"rssi":100,"noise":1,"delta":-2.308,"sysTime":"2018-10-03T07:05:13.979+0300"},{"_id":"5bb43ed2ae55d501a40dfec3","device":"xDrip-DexcomG5","date":1538539213749,"dateString":"2018-10-03T07:00:13.749+0300","sgv":119,"direction":"Flat","type":"sgv","filtered":139392,"unfiltered":137472,"rssi":100,"noise":1,"delta":-0.215,"sysTime":"2018-10-03T07:00:13.749+0300"},{"_id":"5bb43da7ae55d501a40df61e","device":"xDrip-DexcomG5","date":1538538912900,"dateString":"2018-10-03T06:55:12.900+0300","sgv":119,"direction":"Flat","type":"sgv","filtered":139616,"unfiltered":137696,"rssi":100,"noise":1,"delta":-1.523,"sysTime":"2018-10-03T06:55:12.900+0300"},{"_id":"5bb43c7cae55d501a40dea86","device":"xDrip-DexcomG5","date":1538538615722,"dateString":"2018-10-03T06:50:15.722+0300","sgv":121,"direction":"Flat","type":"sgv","filtered":138144,"unfiltered":139264,"rssi":100,"noise":1,"delta":-0.518,"sysTime":"2018-10-03T06:50:15.722+0300"},{"_id":"5bb43b4dae55d501a40ddd35","device":"xDrip-DexcomG5","date":1538538312337,"dateString":"2018-10-03T06:45:12.337+0300","sgv":121,"direction":"Flat","type":"sgv","filtered":134976,"unfiltered":139808,"rssi":100,"noise":1,"delta":2.415,"sysTime":"2018-10-03T06:45:12.337+0300"},{"_id":"5bb43a22ae55d501a40dd277","device":"xDrip-DexcomG5","date":1538538013973,"dateString":"2018-10-03T06:40:13.973+0300","sgv":119,"direction":"FortyFiveUp","type":"sgv","filtered":130256,"unfiltered":137312,"rssi":100,"noise":1,"delta":5.036,"sysTime":"2018-10-03T06:40:13.973+0300"},{"_id":"5bb438f7ae55d501a40dc5bb","device":"xDrip-DexcomG5","date":1538537713154,"dateString":"2018-10-03T06:35:13.154+0300","sgv":114,"direction":"Flat","type":"sgv","filtered":124016,"unfiltered":132064,"rssi":100,"noise":1,"delta":4.144,"sysTime":"2018-10-03T06:35:13.154+0300"},{"_id":"5bb437c7ae55d501a40db829","device":"xDrip-DexcomG5","date":1538537412213,"dateString":"2018-10-03T06:30:12.213+0300","sgv":109,"direction":"FortyFiveUp","type":"sgv","filtered":116480,"unfiltered":127744,"rssi":100,"noise":1,"delta":6.037,"sysTime":"2018-10-03T06:30:12.213+0300"},{"_id":"5bb4369aae55d501a40dacbe","device":"xDrip-DexcomG5","date":1538537112297,"dateString":"2018-10-03T06:25:12.297+0300","sgv":103,"direction":"FortyFiveUp","type":"sgv","filtered":108352,"unfiltered":121472,"rssi":100,"noise":1,"delta":8.183,"sysTime":"2018-10-03T06:25:12.297+0300"},{"_id":"5bb4356fae55d501a40da002","device":"xDrip-DexcomG5","date":1538536812559,"dateString":"2018-10-03T06:20:12.559+0300","sgv":95,"direction":"FortyFiveUp","type":"sgv","filtered":100560,"unfiltered":112976,"rssi":100,"noise":1,"delta":8.291,"sysTime":"2018-10-03T06:20:12.559+0300"},{"_id":"5bb43443ae55d501a40d9576","device":"xDrip-DexcomG5","date":1538536512261,"dateString":"2018-10-03T06:15:12.261+0300","sgv":87,"direction":"FortyFiveUp","type":"sgv","filtered":94080,"unfiltered":104352,"rssi":100,"noise":1,"delta":5.713,"sysTime":"2018-10-03T06:15:12.261+0300"},{"_id":"5bb43317ae55d501a40d89d7","device":"xDrip-DexcomG5","date":1538536212313,"dateString":"2018-10-03T06:10:12.313+0300","sgv":81,"direction":"FortyFiveUp","type":"sgv","filtered":89920,"unfiltered":98416,"rssi":100,"noise":1,"delta":5.419,"sysTime":"2018-10-03T06:10:12.313+0300"},{"_id":"5bb431ecae55d501a40d7ec6","device":"xDrip-DexcomG5","date":1538535913132,"dateString":"2018-10-03T06:05:13.132+0300","sgv":76,"direction":"FortyFiveUp","type":"sgv","filtered":88368,"unfiltered":92800,"rssi":100,"noise":1,"delta":5.181,"sysTime":"2018-10-03T06:05:13.132+0300"},{"_id":"5bb430c1ae55d501a40d7533","device":"xDrip-DexcomG5","date":1538535612704,"dateString":"2018-10-03T06:00:12.704+0300","sgv":71,"direction":"Flat","type":"sgv","filtered":88528,"unfiltered":87408,"rssi":100,"noise":1,"delta":0.2,"sysTime":"2018-10-03T06:00:12.704+0300"},{"_id":"5bb42f93ae55d501a40d691c","device":"xDrip-DexcomG5","date":1538535312578,"dateString":"2018-10-03T05:55:12.578+0300","sgv":70,"direction":"Flat","type":"sgv","filtered":88832,"unfiltered":87200,"rssi":100,"noise":1,"delta":-0.854,"sysTime":"2018-10-03T05:55:12.578+0300"},{"_id":"5bb42d3bae55d501a40d53b3","device":"xDrip-DexcomG5","date":1538534712527,"dateString":"2018-10-03T05:45:12.527+0300","sgv":72,"direction":"Flat","type":"sgv","filtered":87104,"unfiltered":88976,"rssi":100,"noise":1,"delta":1.189,"sysTime":"2018-10-03T05:45:12.527+0300"},{"_id":"5bb42ae5ae55d501a40d3bf2","device":"xDrip-DexcomG5","date":1538534114081,"dateString":"2018-10-03T05:35:14.081+0300","sgv":70,"direction":"Flat","type":"sgv","filtered":84992,"unfiltered":86512,"rssi":100,"noise":1,"delta":1.147,"sysTime":"2018-10-03T05:35:14.081+0300"},{"_id":"5bb429b6ae55d501a40d3204","device":"xDrip-DexcomG5","date":1538533812084,"dateString":"2018-10-03T05:30:12.084+0300","sgv":69,"direction":"Flat","type":"sgv","filtered":84448,"unfiltered":85312,"rssi":100,"noise":1,"delta":0.585,"sysTime":"2018-10-03T05:30:12.084+0300"},{"_id":"5bb4288bae55d501a40d26f3","device":"xDrip-DexcomG5","date":1538533512070,"dateString":"2018-10-03T05:25:12.070+0300","sgv":68,"direction":"Flat","type":"sgv","filtered":84128,"unfiltered":84704,"rssi":100,"noise":1,"delta":0.355,"sysTime":"2018-10-03T05:25:12.070+0300"},{"_id":"5bb4275fae55d501a40d1bfa","device":"xDrip-DexcomG5","date":1538533212433,"dateString":"2018-10-03T05:20:12.433+0300","sgv":68,"direction":"Flat","type":"sgv","filtered":84016,"unfiltered":84336,"rssi":100,"noise":1,"delta":0.369,"sysTime":"2018-10-03T05:20:12.433+0300"},{"_id":"5bb42633ae55d501a40d133c","device":"xDrip-DexcomG5","date":1538532912280,"dateString":"2018-10-03T05:15:12.280+0300","sgv":67,"direction":"Flat","type":"sgv","filtered":84064,"unfiltered":83952,"rssi":100,"noise":1,"delta":-0.139,"sysTime":"2018-10-03T05:15:12.280+0300"},{"_id":"5bb42507ae55d501a40d0851","device":"xDrip-DexcomG5","date":1538532612288,"dateString":"2018-10-03T05:10:12.288+0300","sgv":67,"direction":"Flat","type":"sgv","filtered":84304,"unfiltered":84096,"rssi":100,"noise":1,"delta":-0.123,"sysTime":"2018-10-03T05:10:12.288+0300"},{"_id":"5bb423dbae55d501a40cfd20","device":"xDrip-DexcomG5","date":1538532312485,"dateString":"2018-10-03T05:05:12.485+0300","sgv":68,"direction":"Flat","type":"sgv","filtered":84832,"unfiltered":84224,"rssi":100,"noise":1,"delta":-0.354,"sysTime":"2018-10-03T05:05:12.485+0300"},{"_id":"5bb422afae55d501a40cf45f","device":"xDrip-DexcomG5","date":1538532012375,"dateString":"2018-10-03T05:00:12.375+0300","sgv":68,"direction":"Flat","type":"sgv","filtered":85696,"unfiltered":84592,"rssi":100,"noise":1,"delta":-0.571,"sysTime":"2018-10-03T05:00:12.375+0300"},{"_id":"5bb42184ae55d501a40ce967","device":"xDrip-DexcomG5","date":1538531713291,"dateString":"2018-10-03T04:55:13.291+0300","sgv":68,"direction":"Flat","type":"sgv","filtered":86784,"unfiltered":85184,"rssi":100,"noise":1,"delta":-0.86,"sysTime":"2018-10-03T04:55:13.291+0300"},{"_id":"5bb42056ae55d501a40cddf1","device":"xDrip-DexcomG5","date":1538531412371,"dateString":"2018-10-03T04:50:12.371+0300","sgv":69,"direction":"Flat","type":"sgv","filtered":87872,"unfiltered":86080,"rssi":100,"noise":1,"delta":-0.894,"sysTime":"2018-10-03T04:50:12.371+0300"},{"_id":"5bb41f2bae55d501a40cd549","device":"xDrip-DexcomG5","date":1538531112593,"dateString":"2018-10-03T04:45:12.593+0300","sgv":70,"direction":"Flat","type":"sgv","filtered":88720,"unfiltered":87008,"rssi":100,"noise":1,"delta":-1.477,"sysTime":"2018-10-03T04:45:12.593+0300"},{"_id":"5bb41dffae55d501a40cca1b","device":"xDrip-DexcomG5","date":1538530812340,"dateString":"2018-10-03T04:40:12.340+0300","sgv":72,"direction":"Flat","type":"sgv","filtered":89344,"unfiltered":88544,"rssi":100,"noise":1,"delta":-0.647,"sysTime":"2018-10-03T04:40:12.340+0300"},{"_id":"5bb41cd3ae55d501a40cbec2","device":"xDrip-DexcomG5","date":1538530512615,"dateString":"2018-10-03T04:35:12.615+0300","sgv":72,"direction":"Flat","type":"sgv","filtered":89792,"unfiltered":89216,"rssi":100,"noise":1,"delta":-0.246,"sysTime":"2018-10-03T04:35:12.615+0300"},{"_id":"5bb41ba7ae55d501a40cb5a4","device":"xDrip-DexcomG5","date":1538530212379,"dateString":"2018-10-03T04:30:12.379+0300","sgv":73,"direction":"Flat","type":"sgv","filtered":90112,"unfiltered":89472,"rssi":100,"noise":1,"delta":-0.324,"sysTime":"2018-10-03T04:30:12.379+0300"},{"_id":"5bb41a7bae55d501a40caa72","device":"xDrip-DexcomG5","date":1538529912710,"dateString":"2018-10-03T04:25:12.710+0300","sgv":73,"direction":"Flat","type":"sgv","filtered":90272,"unfiltered":89808,"rssi":100,"noise":1,"delta":-0.554,"sysTime":"2018-10-03T04:25:12.710+0300"},{"_id":"5bb4194fae55d501a40c9ee6","device":"xDrip-DexcomG5","date":1538529612382,"dateString":"2018-10-03T04:20:12.382+0300","sgv":73,"direction":"Flat","type":"sgv","filtered":90384,"unfiltered":90384,"rssi":100,"noise":1,"delta":-0.169,"sysTime":"2018-10-03T04:20:12.382+0300"},{"_id":"5bb41823ae55d501a40c962b","device":"xDrip-DexcomG5","date":1538529312426,"dateString":"2018-10-03T04:15:12.426+0300","sgv":74,"direction":"Flat","type":"sgv","filtered":90720,"unfiltered":90560,"rssi":100,"noise":1,"delta":-0.077,"sysTime":"2018-10-03T04:15:12.426+0300"},{"_id":"5bb416f7ae55d501a40c8b27","device":"xDrip-DexcomG5","date":1538529012437,"dateString":"2018-10-03T04:10:12.437+0300","sgv":74,"direction":"Flat","type":"sgv","filtered":91456,"unfiltered":90640,"rssi":100,"noise":1,"delta":-0.246,"sysTime":"2018-10-03T04:10:12.437+0300"},{"_id":"5bb415cbae55d501a40c7fe3","device":"xDrip-DexcomG5","date":1538528712343,"dateString":"2018-10-03T04:05:12.343+0300","sgv":74,"direction":"Flat","type":"sgv","filtered":92592,"unfiltered":90896,"rssi":100,"noise":1,"delta":-1.032,"sysTime":"2018-10-03T04:05:12.343+0300"},{"_id":"5bb4149fae55d501a40c770b","device":"xDrip-DexcomG5","date":1538528412402,"dateString":"2018-10-03T04:00:12.402+0300","sgv":75,"direction":"Flat","type":"sgv","filtered":93888,"unfiltered":91968,"rssi":100,"noise":1,"delta":-0.985,"sysTime":"2018-10-03T04:00:12.402+0300"},{"_id":"5bb41373ae55d501a40c6c62","device":"xDrip-DexcomG5","date":1538528112264,"dateString":"2018-10-03T03:55:12.264+0300","sgv":76,"direction":"Flat","type":"sgv","filtered":94976,"unfiltered":92992,"rssi":100,"noise":1,"delta":-1.083,"sysTime":"2018-10-03T03:55:12.264+0300"},{"_id":"5bb41248ae55d501a40c6142","device":"xDrip-DexcomG5","date":1538527813723,"dateString":"2018-10-03T03:50:13.723+0300","sgv":77,"direction":"Flat","type":"sgv","filtered":95792,"unfiltered":94112,"rssi":100,"noise":1,"delta":-1.685,"sysTime":"2018-10-03T03:50:13.723+0300"},{"_id":"5bb4111aae55d501a40c5829","device":"xDrip-DexcomG5","date":1538527512108,"dateString":"2018-10-03T03:45:12.108+0300","sgv":79,"direction":"Flat","type":"sgv","filtered":96496,"unfiltered":95872,"rssi":100,"noise":1,"delta":-0.478,"sysTime":"2018-10-03T03:45:12.108+0300"},{"_id":"5bb40fefae55d501a40c4c0d","device":"xDrip-DexcomG5","date":1538527212845,"dateString":"2018-10-03T03:40:12.845+0300","sgv":79,"direction":"Flat","type":"sgv","filtered":97472,"unfiltered":96368,"rssi":100,"noise":1,"delta":-0.553,"sysTime":"2018-10-03T03:40:12.845+0300"},{"_id":"5bb40ec3ae55d501a40c3fa8","device":"xDrip-DexcomG5","date":1538526912171,"dateString":"2018-10-03T03:35:12.171+0300","sgv":80,"direction":"Flat","type":"sgv","filtered":98864,"unfiltered":96944,"rssi":100,"noise":1,"delta":-0.956,"sysTime":"2018-10-03T03:35:12.171+0300"},{"_id":"5bb40d97ae55d501a40c35dd","device":"xDrip-DexcomG5","date":1538526612563,"dateString":"2018-10-03T03:30:12.563+0300","sgv":81,"direction":"Flat","type":"sgv","filtered":100464,"unfiltered":97936,"rssi":100,"noise":1,"delta":-1.4,"sysTime":"2018-10-03T03:30:12.563+0300"},{"_id":"5bb40c6bae55d501a40c2999","device":"xDrip-DexcomG5","date":1538526312393,"dateString":"2018-10-03T03:25:12.393+0300","sgv":82,"direction":"Flat","type":"sgv","filtered":101920,"unfiltered":99392,"rssi":100,"noise":1,"delta":-1.619,"sysTime":"2018-10-03T03:25:12.393+0300"},{"_id":"5bb40b3fae55d501a40c1d8d","device":"xDrip-DexcomG5","date":1538526012755,"dateString":"2018-10-03T03:20:12.755+0300","sgv":84,"direction":"Flat","type":"sgv","filtered":103088,"unfiltered":101072,"rssi":100,"noise":1,"delta":-1.492,"sysTime":"2018-10-03T03:20:12.755+0300"},{"_id":"5bb40a12ae55d501a40c13df","device":"xDrip-DexcomG5","date":1538525712365,"dateString":"2018-10-03T03:15:12.365+0300","sgv":85,"direction":"Flat","type":"sgv","filtered":104208,"unfiltered":102624,"rssi":100,"noise":1,"delta":-1.4,"sysTime":"2018-10-03T03:15:12.365+0300"},{"_id":"5bb408e6ae55d501a40c0829","device":"xDrip-DexcomG5","date":1538525412236,"dateString":"2018-10-03T03:10:12.236+0300","sgv":87,"direction":"Flat","type":"sgv","filtered":105776,"unfiltered":104080,"rssi":100,"noise":1,"delta":-1.066,"sysTime":"2018-10-03T03:10:12.236+0300"},{"_id":"5bb407bdae55d501a40bfd32","device":"xDrip-DexcomG5","date":1538525113399,"dateString":"2018-10-03T03:05:13.399+0300","sgv":88,"direction":"Flat","type":"sgv","filtered":108096,"unfiltered":105184,"rssi":100,"noise":1,"delta":-1.247,"sysTime":"2018-10-03T03:05:13.399+0300"},{"_id":"5bb40690ae55d501a40bf40c","device":"xDrip-DexcomG5","date":1538524813354,"dateString":"2018-10-03T03:00:13.354+0300","sgv":89,"direction":"Flat","type":"sgv","filtered":110960,"unfiltered":106480,"rssi":100,"noise":1,"delta":-2.41,"sysTime":"2018-10-03T03:00:13.354+0300"},{"_id":"5bb40563ae55d501a40be905","device":"xDrip-DexcomG5","date":1538524512502,"dateString":"2018-10-03T02:55:12.502+0300","sgv":91,"direction":"Flat","type":"sgv","filtered":113824,"unfiltered":108992,"rssi":100,"noise":1,"delta":-2.944,"sysTime":"2018-10-03T02:55:12.502+0300"},{"_id":"5bb40437ae55d501a40bddc7","device":"xDrip-DexcomG5","date":1538524212815,"dateString":"2018-10-03T02:50:12.815+0300","sgv":94,"direction":"Flat","type":"sgv","filtered":116416,"unfiltered":112048,"rssi":100,"noise":1,"delta":-3.507,"sysTime":"2018-10-03T02:50:12.815+0300"},{"_id":"5bb4030bae55d501a40bd4e3","device":"xDrip-DexcomG5","date":1538523912480,"dateString":"2018-10-03T02:45:12.480+0300","sgv":98,"direction":"Flat","type":"sgv","filtered":118864,"unfiltered":115696,"rssi":100,"noise":1,"delta":-2.063,"sysTime":"2018-10-03T02:45:12.480+0300"},{"_id":"5bb401dfae55d501a40bc9da","device":"xDrip-DexcomG5","date":1538523612471,"dateString":"2018-10-03T02:40:12.471+0300","sgv":100,"direction":"Flat","type":"sgv","filtered":121152,"unfiltered":117840,"rssi":100,"noise":1,"delta":-1.204,"sysTime":"2018-10-03T02:40:12.471+0300"},{"_id":"5bb400b4ae55d501a40bbee5","device":"xDrip-DexcomG5","date":1538523313312,"dateString":"2018-10-03T02:35:13.312+0300","sgv":101,"direction":"Flat","type":"sgv","filtered":123104,"unfiltered":119088,"rssi":100,"noise":1,"delta":-3.044,"sysTime":"2018-10-03T02:35:13.312+0300"},{"_id":"5bb3ff87ae55d501a40bb615","device":"xDrip-DexcomG5","date":1538523012870,"dateString":"2018-10-03T02:30:12.870+0300","sgv":104,"direction":"Flat","type":"sgv","filtered":124576,"unfiltered":122256,"rssi":100,"noise":1,"delta":-1.558,"sysTime":"2018-10-03T02:30:12.870+0300"},{"_id":"5bb3fd30ae55d501a40ba04d","device":"xDrip-DexcomG5","date":1538522414042,"dateString":"2018-10-03T02:20:14.042+0300","sgv":107,"direction":"Flat","type":"sgv","filtered":127440,"unfiltered":125488,"rssi":100,"noise":1,"delta":-0.905,"sysTime":"2018-10-03T02:20:14.042+0300"},{"_id":"5bb3fc04ae55d501a40b9779","device":"xDrip-DexcomG5","date":1538522113058,"dateString":"2018-10-03T02:15:13.058+0300","sgv":108,"direction":"Flat","type":"sgv","filtered":129360.00000000001,"unfiltered":126432,"rssi":100,"noise":1,"delta":-1.756,"sysTime":"2018-10-03T02:15:13.058+0300"},{"_id":"5bb3f9acae55d501a40b80b5","device":"xDrip-DexcomG5","date":1538521513479,"dateString":"2018-10-03T02:05:13.479+0300","sgv":112,"direction":"Flat","type":"sgv","filtered":133120,"unfiltered":130080.00000000001,"rssi":100,"noise":1,"delta":-2.398,"sysTime":"2018-10-03T02:05:13.479+0300"},{"_id":"5bb3f87fae55d501a40b7678","device":"xDrip-DexcomG5","date":1538521212940,"dateString":"2018-10-03T02:00:12.940+0300","sgv":114,"direction":"Flat","type":"sgv","filtered":134912,"unfiltered":132576,"rssi":100,"noise":1,"delta":-1.416,"sysTime":"2018-10-03T02:00:12.940+0300"},{"_id":"5bb3f753ae55d501a40b6977","device":"xDrip-DexcomG5","date":1538520912923,"dateString":"2018-10-03T01:55:12.923+0300","sgv":116,"direction":"Flat","type":"sgv","filtered":136768,"unfiltered":134048,"rssi":100,"noise":1,"delta":-1.633,"sysTime":"2018-10-03T01:55:12.923+0300"},{"_id":"5bb3f628ae55d501a40b5cdc","device":"xDrip-DexcomG5","date":1538520613094,"dateString":"2018-10-03T01:50:13.094+0300","sgv":117,"direction":"Flat","type":"sgv","filtered":138688,"unfiltered":135744,"rssi":100,"noise":1,"delta":-1.635,"sysTime":"2018-10-03T01:50:13.094+0300"},{"_id":"5bb3f4fcae55d501a40b529f","device":"xDrip-DexcomG5","date":1538520313580,"dateString":"2018-10-03T01:45:13.580+0300","sgv":119,"direction":"Flat","type":"sgv","filtered":140288,"unfiltered":137440,"rssi":100,"noise":1,"delta":-1.814,"sysTime":"2018-10-03T01:45:13.580+0300"},{"_id":"5bb3f3cfae55d501a40b465f","device":"xDrip-DexcomG5","date":1538520013042,"dateString":"2018-10-03T01:40:13.042+0300","sgv":121,"direction":"Flat","type":"sgv","filtered":141408,"unfiltered":139328,"rssi":100,"noise":1,"delta":-1.668,"sysTime":"2018-10-03T01:40:13.042+0300"},{"_id":"5bb3f2a4ae55d501a40b39f2","device":"xDrip-DexcomG5","date":1538519713908,"dateString":"2018-10-03T01:35:13.908+0300","sgv":122,"direction":"Flat","type":"sgv","filtered":142240,"unfiltered":141056,"rssi":100,"noise":1,"delta":-1.261,"sysTime":"2018-10-03T01:35:13.908+0300"},{"_id":"5bb3f178ae55d501a40b2fd8","device":"xDrip-DexcomG5","date":1538519413545,"dateString":"2018-10-03T01:30:13.545+0300","sgv":124,"direction":"Flat","type":"sgv","filtered":142880,"unfiltered":142368,"rssi":100,"noise":1,"delta":0.123,"sysTime":"2018-10-03T01:30:13.545+0300"},{"_id":"5bb3f04bae55d501a40b2380","device":"xDrip-DexcomG5","date":1538519112616,"dateString":"2018-10-03T01:25:12.616+0300","sgv":123,"direction":"Flat","type":"sgv","filtered":143072,"unfiltered":142240,"rssi":100,"noise":1,"delta":-0.062,"sysTime":"2018-10-03T01:25:12.616+0300"},{"_id":"5bb3ef1fae55d501a40b1703","device":"xDrip-DexcomG5","date":1538518812821,"dateString":"2018-10-03T01:20:12.821+0300","sgv":123,"direction":"Flat","type":"sgv","filtered":142496,"unfiltered":142304,"rssi":100,"noise":1,"delta":-0.834,"sysTime":"2018-10-03T01:20:12.821+0300"},{"_id":"5bb3edf4ae55d501a40b0cf0","device":"xDrip-DexcomG5","date":1538518513642,"dateString":"2018-10-03T01:15:13.642+0300","sgv":124,"direction":"Flat","type":"sgv","filtered":141216,"unfiltered":143168,"rssi":100,"noise":1,"delta":0.523,"sysTime":"2018-10-03T01:15:13.642+0300"},{"_id":"5bb3eb9bae55d501a40af401","device":"xDrip-DexcomG5","date":1538517913085,"dateString":"2018-10-03T01:05:13.085+0300","sgv":123,"direction":"Flat","type":"sgv","filtered":140640,"unfiltered":142080,"rssi":100,"noise":1,"delta":2.49,"sysTime":"2018-10-03T01:05:13.085+0300"},{"_id":"5bb3ea70ae55d501a40ae9a5","device":"xDrip-DexcomG5","date":1538517612593,"dateString":"2018-10-03T01:00:12.593+0300","sgv":121,"direction":"Flat","type":"sgv","filtered":141536,"unfiltered":139488,"rssi":100,"noise":1,"delta":-0.369,"sysTime":"2018-10-03T01:00:12.593+0300"},{"_id":"5bb3e942ae55d501a40adcc6","device":"xDrip-DexcomG5","date":1538517312497,"dateString":"2018-10-03T00:55:12.497+0300","sgv":121,"direction":"Flat","type":"sgv","filtered":141504,"unfiltered":139872,"rssi":100,"noise":1,"delta":-0.585,"sysTime":"2018-10-03T00:55:12.497+0300"},{"_id":"5bb3e817ae55d501a40ad00b","device":"xDrip-DexcomG5","date":1538517012662,"dateString":"2018-10-03T00:50:12.662+0300","sgv":122,"direction":"Flat","type":"sgv","filtered":139456,"unfiltered":140480,"rssi":100,"noise":1,"delta":-0.895,"sysTime":"2018-10-03T00:50:12.662+0300"},{"_id":"5bb3e6ecae55d501a40ac558","device":"xDrip-DexcomG5","date":1538516713313,"dateString":"2018-10-03T00:45:13.313+0300","sgv":123,"direction":"Flat","type":"sgv","filtered":137216,"unfiltered":141408,"rssi":100,"noise":1,"delta":-1.445,"sysTime":"2018-10-03T00:45:13.313+0300"},{"_id":"5bb3e5bfae55d501a40ab6c1","device":"xDrip-DexcomG5","date":1538516412928,"dateString":"2018-10-03T00:40:12.928+0300","sgv":124,"direction":"FortyFiveUp","type":"sgv","filtered":137280,"unfiltered":142912,"rssi":100,"noise":1,"delta":6.491,"sysTime":"2018-10-03T00:40:12.928+0300"},{"_id":"5bb3e493ae55d501a40aa654","device":"xDrip-DexcomG5","date":1538516112636,"dateString":"2018-10-03T00:35:12.636+0300","sgv":118,"direction":"Flat","type":"sgv","filtered":139904,"unfiltered":136160,"rssi":100,"noise":1,"delta":2.153,"sysTime":"2018-10-03T00:35:12.636+0300"},{"_id":"5bb3e367ae55d501a40a955c","device":"xDrip-DexcomG5","date":1538515812303,"dateString":"2018-10-03T00:30:12.303+0300","sgv":115,"direction":"FortyFiveDown","type":"sgv","filtered":143360,"unfiltered":133920,"rssi":100,"noise":1,"delta":-8.499,"sysTime":"2018-10-03T00:30:12.303+0300"},{"_id":"5bb3e23bae55d501a40a84ca","device":"xDrip-DexcomG5","date":1538515512299,"dateString":"2018-10-03T00:25:12.299+0300","sgv":124,"direction":"Flat","type":"sgv","filtered":145792,"unfiltered":142752,"rssi":100,"noise":1,"delta":-2.789,"sysTime":"2018-10-03T00:25:12.299+0300"},{"_id":"5bb3e114ae55d501a40a7256","device":"xDrip-DexcomG5","date":1538515217494,"dateString":"2018-10-03T00:20:17.494+0300","sgv":127,"direction":"Flat","type":"sgv","filtered":147136,"unfiltered":145600,"rssi":100,"noise":1,"delta":-0.455,"sysTime":"2018-10-03T00:20:17.494+0300"},{"_id":"5bb3dfe3ae55d501a40a62ea","device":"xDrip-DexcomG5","date":1538514913199,"dateString":"2018-10-03T00:15:13.199+0300","sgv":127,"direction":"Flat","type":"sgv","filtered":148384,"unfiltered":146080,"rssi":100,"noise":1,"delta":-1.85,"sysTime":"2018-10-03T00:15:13.199+0300"},{"_id":"5bb3deb8ae55d501a40a5044","device":"xDrip-DexcomG5","date":1538514613615,"dateString":"2018-10-03T00:10:13.615+0300","sgv":129,"direction":"Flat","type":"sgv","filtered":150144,"unfiltered":148000,"rssi":100,"noise":1,"delta":-1.787,"sysTime":"2018-10-03T00:10:13.615+0300"},{"_id":"5bb3dd8cae55d501a40a406d","device":"xDrip-DexcomG5","date":1538514313780,"dateString":"2018-10-03T00:05:13.780+0300","sgv":131,"direction":"Flat","type":"sgv","filtered":152896,"unfiltered":149856,"rssi":100,"noise":1,"delta":-1.969,"sysTime":"2018-10-03T00:05:13.780+0300"}]